nonebot_plugin_idiom/__init__.py
nonebot_plugin_idiom/idiom.json
nonebot_plugin_idiom-0.1.4.dist-info/LICENSE
nonebot_plugin_idiom-0.1.4.dist-info/METADATA
nonebot_plugin_idiom-0.1.4.dist-info/WHEEL
nonebot_plugin_idiom-0.1.4.dist-info/RECORD
