Metadata-Version: 2.1
Name: nonebot-plugin-idiom
Version: 0.1.4
Summary: 
Author: Your dxn
Author-email: 1684193123@qq.com
Requires-Python: >=3.7,<4.0
Classifier: Programming Language :: Python :: 3
Classifier: Programming Language :: Python :: 3.7
Classifier: Programming Language :: Python :: 3.8
Classifier: Programming Language :: Python :: 3.9
Classifier: Programming Language :: Python :: 3.10
Classifier: Programming Language :: Python :: 3.11
Requires-Dist: nonebot-adapter-onebot (>=2.1.3,<3.0.0)
Requires-Dist: nonebot2 (>=2.0.0b5,<3.0.0)
